ebook_mcp/__init__.py
ebook_mcp/main.py
ebook_mcp/mcp_client_example/.gitignore
ebook_mcp/mcp_client_example/README-CN.md
ebook_mcp/mcp_client_example/README.md
ebook_mcp/mcp_client_example/anthropic_example.py
ebook_mcp/mcp_client_example/deepseek_example.py
ebook_mcp/mcp_client_example/openai_example.py
ebook_mcp/mcp_client_example/pyproject.toml
ebook_mcp/mcp_client_example/requirements.txt
ebook_mcp/tests/conftest.py
ebook_mcp/tests/run_tests.py
ebook_mcp/tests/test_azw.py
ebook_mcp/tests/test_basic.py
ebook_mcp/tests/test_epub_chapter_extraction.py
ebook_mcp/tests/test_epub_helper.py
ebook_mcp/tests/test_logger_config.py
ebook_mcp/tests/test_main.py
ebook_mcp/tests/test_pdf_helper.py
ebook_mcp/tools/epub_helper.py
ebook_mcp/tools/logger_config.py
ebook_mcp/tools/pdf_helper.py
ebook_mcp/tools/pdf_helper.py.backup
ebook_mcp-0.1.8.dist-info/METADATA
ebook_mcp-0.1.8.dist-info/WHEEL
ebook_mcp-0.1.8.dist-info/entry_points.txt
ebook_mcp-0.1.8.dist-info/licenses/LICENSE
ebook_mcp-0.1.8.dist-info/RECORD
